{
  "url": "https://www.mediaworld.it/it/category/notebook-200101.html",
  "timestamp": "2025-08-26T11:18:26.974898",
  "result": {
    "success": true,
    "products": [
      {
        "name": "MICROSOFT Surface Pro Copilot+ PC convertibile 2 in 1",
        "price": "€1.477,99",
        "brand": "MICROSOFT",
        "model": "Surface Pro Copilot+",
        "weight": null,
        "price_per_kg": null,
        "rating": "16",
        "description": "PC convertibile 2 in 1, 13 \", processore Qualcomm Snapdragon X Elite X1E-80-100, 16 GB, 512 GB SSD, Dune, Touchscreen OLED, Windows 11 Home",
        "category": "Computers",
        "availability": "In Stock",
        "warranty": null,
        "specs": {
          "processor": "Qualcomm Snapdragon X Elite X1E-80-100",
          "RAM": "16 GB",
          "SSD": "512 GB",
          "screen": "13\" Touchscreen OLED",
          "OS": "Windows 11 Home"
        }
      },
      {
        "name": "ACER Chromebook 314 CBOA314-1H",
        "price": "€179,00",
        "brand": "ACER",
        "model": "CBOA314-1H",
        "weight": null,
        "price_per_kg": null,
        "rating": "6",
        "description": "14 \", processore Intel® Celeron N4500, 4 GB, 64 GB eMMC, Black",
        "category": "Chromebooks",
        "availability": "In Stock",
        "warranty": null,
        "specs": {
          "processor": "Intel® Celeron N4500",
          "RAM": "4 GB",
          "storage": "64 GB eMMC",
          "graphics": "UHD Graphics"
        }
      },
      {
        "name": "ACER Chromebook Spin CP513-1H",
        "price": "€199,00",
        "brand": "ACER",
        "model": "CP513-1H",
        "weight": null,
        "price_per_kg": null,
        "rating": "2",
        "description": "13,3 \", processore Qualcomm Snapdragon SC7 180 SC7180, QUALCOMM ADRENO 618, 4 GB, 64 GB eMMC, Argento",
        "category": "Chromebooks",
        "availability": "In Stock",
        "warranty": null,
        "specs": {
          "processor": "Qualcomm Snapdragon SC7 180 SC7180",
          "RAM": "4 GB",
          "storage": "64 GB eMMC",
          "OS": "Chrome OS7"
        }
      },
      {
        "name": "APPLE MacBook Air 13''",
        "price": "€979,00",
        "brand": "APPLE",
        "model": "MacBook Air",
        "weight": null,
        "price_per_kg": null,
        "rating": "34",
        "description": "Chip M4, 10 CPU 8 GPU, 16GB, 256GB, Mezzanotte",
        "category": "Laptops",
        "availability": "In Stock",
        "warranty": null,
        "specs": {
          "processor": "M4 CPU 10-core",
          "RAM": "16 GB",
          "storage": "256 GB",
          "OS": "macOS Sequoia"
        }
      },
      {
        "name": "APPLE MacBook Air 13''",
        "price": "€979,00",
        "brand": "APPLE",
        "model": "MacBook Air",
        "weight": null,
        "price_per_kg": null,
        "rating": "34",
        "description": "Chip M4, 10 CPU 8 GPU, 16GB, 256GB, Galassia",
        "category": "Laptops",
        "availability": "In Stock",
        "warranty": null,
        "specs": {
          "processor": "M4 CPU 10-core",
          "RAM": "16 GB",
          "storage": "256 GB",
          "OS": "macOS Sequoia"
        }
      },
      {
        "name": "APPLE MacBook Air 13''",
        "price": "€979,00",
        "brand": "APPLE",
        "model": "MacBook Air",
        "weight": null,
        "price_per_kg": null,
        "rating": "34",
        "description": "Chip M4, 10 CPU 8 GPU, 16GB, 256GB, Argento",
        "category": "Laptops",
        "availability": "In Stock",
        "warranty": null,
        "specs": {
          "processor": "M4 CPU 10-core",
          "RAM": "16 GB",
          "storage": "256 GB",
          "OS": "macOS Sequoia"
        }
      },
      {
        "name": "APPLE MacBook Air 13''",
        "price": "€1.349,00",
        "brand": "APPLE",
        "model": "MacBook Air",
        "weight": null,
        "price_per_kg": null,
        "rating": "11",
        "description": "Chip M4, 10 CPU 10 GPU, 16GB, 512GB, Mezzanotte",
        "category": "Laptops",
        "availability": "In Stock",
        "warranty": null,
        "specs": {
          "processor": "M4 CPU 10-core",
          "RAM": "16 GB",
          "storage": "512 GB",
          "OS": "macOS Sequoia"
        }
      },
      {
        "name": "ASUS Vivobook 16 X1605",
        "price": "€949,00",
        "brand": "ASUS",
        "model": "X1605",
        "weight": null,
        "price_per_kg": null,
        "rating": "9",
        "description": "16 \", processore Intel® Core I9 13900H, 24 GB, 1000 GB SSD, Argento",
        "category": "Laptops",
        "availability": "In Stock",
        "warranty": null,
        "specs": {
          "processor": "Core I9 13900H",
          "RAM": "24 GB",
          "storage": "1000 GB SSD",
          "graphics": "Iris® Xᵉ"
        }
      },
      {
        "name": "SAMSUNG Galaxy Book4 15.6 i5",
        "price": "€599,00",
        "brand": "SAMSUNG",
        "model": "Galaxy Book4",
        "weight": null,
        "price_per_kg": null,
        "rating": "26",
        "description": "15,6 \", processore Intel® Core I5 1355U, INTEL Iris Xe Graphics, 16 GB, 512 GB SSD, Grey",
        "category": "Laptops",
        "availability": "In Stock",
        "warranty": null,
        "specs": {
          "processor": "Core I5 1355U",
          "RAM": "16 GB",
          "storage": "512 GB SSD",
          "graphics": "Iris® Xᵉ"
        }
      },
      {
        "name": "HP Victus 15-fb3703nl",
        "price": "€899,00",
        "brand": "HP",
        "model": "Victus 15-fb3703nl",
        "weight": null,
        "price_per_kg": null,
        "rating": "1",
        "description": "15,6 \", processore AMD Ryzen 7 8845HS, 16 GB, 1000 GB SSD",
        "category": "Laptops",
        "availability": "In Stock",
        "warranty": null,
        "specs": {
          "processor": "Ryzen 7 8845HS",
          "RAM": "16 GB",
          "storage": "1000 GB SSD",
          "graphics": "GeForce RTX™ 4050"
        }
      },
      {
        "name": "MSI Thin 15 B13VE-2070IT",
        "price": "€849,00",
        "brand": "MSI",
        "model": "Thin 15 B13VE-2070IT",
        "weight": null,
        "price_per_kg": null,
        "rating": "15",
        "description": "15,6 \", processore Intel® Core I7 13620H, NVIDIA GeForce RTX 4050, 16 GB, 512 GB SSD, Grey",
        "category": "Laptops",
        "availability": "In Stock",
        "warranty": null,
        "specs": {
          "processor": "Core I7 13620H",
          "RAM": "16 GB",
          "storage": "512 GB SSD",
          "graphics": "GeForce RTX™ 4050"
        }
      },
      {
        "name": "ASUS HT5306QA-LX004W",
        "price": "€999,00",
        "brand": "ASUS",
        "model": "HT5306QA-LX004W",
        "weight": null,
        "price_per_kg": null,
        "rating": "2",
        "description": "13,3 \", processore Qualcomm Snapdragon X Plus X1P 42 100 , 16 GB, 1000 GB SSD, Black",
        "category": "Laptops",
        "availability": "In Stock",
        "warranty": null,
        "specs": {
          "processor": "Qualcomm Snapdragon X Plus X1P 42 100",
          "RAM": "16 GB",
          "storage": "1000 GB SSD"
        }
      }
    ],
    "total_found": 12,
    "url": "https://www.mediaworld.it/it/category/notebook-200101.html",
    "extraction_method": "saved_selectors",
    "container_selector": "article",
    "containers_found": 19,
    "timestamp": "2025-08-26T11:18:26.962879"
  }
}